lima/__init__.py
lima/client.py
lima_punkbrwstr-0.0.3.dist-info/LICENSE
lima_punkbrwstr-0.0.3.dist-info/METADATA
lima_punkbrwstr-0.0.3.dist-info/WHEEL
lima_punkbrwstr-0.0.3.dist-info/top_level.txt
lima_punkbrwstr-0.0.3.dist-info/RECORD
