Metadata-Version: 2.1
Name: lima-punkbrwstr
Version: 0.0.3
Summary: Column-oriented time series data store in Redis
Home-page: https://github.com/punkbrwstr/lima
Author: Peter Graf
Author-email: magnumpi@gmail.com
License: UNKNOWN
Platform: UNKNOWN
Classifier: Programming Language :: Python :: 3
Classifier: License :: OSI Approved :: MIT License
Classifier: Operating System :: OS Independent
Requires-Dist: hiredis
Requires-Dist: numpy
Requires-Dist: pandas
Requires-Dist: redis
